phyloroot/__init__.py
phyloroot/main_cli.py
phyloroot/rooting.py
phyloroot-0.1.0.dist-info/LICENCE
phyloroot-0.1.0.dist-info/METADATA
phyloroot-0.1.0.dist-info/WHEEL
phyloroot-0.1.0.dist-info/entry_points.txt
phyloroot-0.1.0.dist-info/top_level.txt
phyloroot-0.1.0.dist-info/RECORD
