Metadata-Version: 2.1
Name: phyloroot
Version: 0.1.0
Summary: A package for orienting phylogenetic networks in several well-known classes.
Author-email: Remie Janssen <remiejanssen92@gmail.com>
Project-URL: Homepage, https://github.com/RemieJanssen/RootingNetworks
Project-URL: Bug Tracker, https://github.com/RemieJanssen/RootingNetworks/issues
Classifier: Programming Language :: Python :: 3
Classifier: License :: OSI Approved :: MIT License
Classifier: Operating System :: OS Independent
Requires-Python: >=3.7
License-File: LICENCE
